<annotation>
	<folder>images_v2_resized</folder>
	<filename>IMG_20191130_105737500_resized.jpg</filename>
	<path>/home/cassiano/Dropbox/Univali/Mestrado/semestre2/visao_computacional/images_v2_resized/IMG_20191130_105737500_resized.jpg</path>
	<source>
		<database>Unknown</database>
	</source>
	<size>
		<width>806</width>
		<height>604</height>
		<depth>3</depth>
	</size>
	<segmented>0</segmented>
	<object>
		<name>bumbo</name>
		<pose>Unspecified</pose>
		<truncated>0</truncated>
		<difficult>0</difficult>
		<bndbox>
			<xmin>365</xmin>
			<ymin>44</ymin>
			<xmax>540</xmax>
			<ymax>253</ymax>
		</bndbox>
	</object>
	<object>
		<name>bumbo</name>
		<pose>Unspecified</pose>
		<truncated>0</truncated>
		<difficult>0</difficult>
		<bndbox>
			<xmin>356</xmin>
			<ymin>336</ymin>
			<xmax>507</xmax>
			<ymax>558</ymax>
		</bndbox>
	</object>
</annotation>
